hectiq_console/__init__.py
hectiq_console/functional.py
hectiq_console/upload.py
hectiq_console/cli/__init__.py
hectiq_console/cli/__main__.py
hectiq_console/cli/auth.py
hectiq_console/starlette/__init__.py
hectiq_console/starlette/middleware.py
hectiq_console/utils/__init__.py
hectiq_console/utils/batch_fetch.py
hectiq_console/utils/docstring.py
hectiq_console/utils/log_handler.py
hectiq_console-1.2.4.dist-info/LICENSE
hectiq_console-1.2.4.dist-info/METADATA
hectiq_console-1.2.4.dist-info/WHEEL
hectiq_console-1.2.4.dist-info/entry_points.txt
hectiq_console-1.2.4.dist-info/top_level.txt
hectiq_console-1.2.4.dist-info/RECORD
