Metadata-Version: 2.1
Name: hectiq-console
Version: 1.2.4
Summary: Python client to use the Hectiq Console
Home-page: https://console.hectiq.ai
Author: Edward Laurence
Author-email: edwardl@hectiq.ai
Keywords: pip requirements imports
Classifier: Programming Language :: Python :: 3
Classifier: Intended Audience :: Developers
Classifier: Operating System :: OS Independent
Classifier: Topic :: Software Development :: Libraries :: Python Modules
Classifier: Topic :: Scientific/Engineering
Classifier: Intended Audience :: Science/Research
License-File: LICENSE
Requires-Dist: requests
Requires-Dist: toml
Requires-Dist: pydantic
Requires-Dist: tqdm
Requires-Dist: click
Provides-Extra: starlette
Requires-Dist: starlette ; extra == 'starlette'
